biomes_cayley_py-0.1.0.dist-info/METADATA
biomes_cayley_py-0.1.0.dist-info/WHEEL
cayley/__init__.py
cayley/cayley.cpython-39-x86_64-linux-gnu.so
biomes_cayley_py-0.1.0.dist-info/RECORD
