Metadata-Version: 2.4
Name: biomes-cayley-py
Version: 0.1.0
Classifier: Programming Language :: Rust
Classifier: Programming Language :: Python :: Implementation :: CPython
Classifier: Programming Language :: Python :: Implementation :: PyPy
Summary: Python binding of Biomes's Cayley module.
Author-email: "Wei Ji (FlySkyPie)" <c445dj544@gmail.com>
License: MIT
Requires-Python: >=3.9
